<?xml version="1.0" encoding="utf-8"?>
<doctrine-mapping xmlns="http://doctrine-project.org/schemas/orm/doctrine-mapping"
                  xmlns:xsi="http://www.w3.org/2001/XMLSchema-instance"
                  xsi:schemaLocation="http://doctrine-project.org/schemas/orm/doctrine-mapping http://doctrine-project.org/schemas/orm/doctrine-mapping.xsd">

    <mapped-superclass name="Sulu\Bundle\MediaBundle\Entity\Media" table="me_media"
            repository-class="Sulu\Bundle\MediaBundle\Entity\MediaRepository">
        <indexes>
            <index columns="changed"/>
            <index columns="created"/>
        </indexes>

        <id name="id" type="integer" column="id">
            <generator strategy="AUTO"/>
        </id>

        <one-to-many field="files" target-entity="Sulu\Bundle\MediaBundle\Entity\File" mapped-by="media">
            <cascade>
                <cascade-persist />
            </cascade>
        </one-to-many>

        <many-to-one field="collection" target-entity="Sulu\Bundle\MediaBundle\Entity\CollectionInterface" inversed-by="media">
            <join-columns>
                <join-column name="idCollections" referenced-column-name="id" on-delete="CASCADE" nullable="false"/>
            </join-columns>
        </many-to-one>
        <many-to-one field="type" target-entity="Sulu\Bundle\MediaBundle\Entity\MediaType" inversed-by="media">
            <join-columns>
                <join-column name="idMediaTypes" referenced-column-name="id" nullable="false"/>
            </join-columns>
        </many-to-one>

        <one-to-one field="previewImage" target-entity="Sulu\Bundle\MediaBundle\Entity\MediaInterface">
            <join-column name="idPreviewImage" referenced-column-name="id"/>
        </one-to-one>
    </mapped-superclass>
</doctrine-mapping>
